src/__init__.py
src/cli.py
src/main.py
auto_subtitles_generator-0.2.0.dist-info/LICENSE
auto_subtitles_generator-0.2.0.dist-info/METADATA
auto_subtitles_generator-0.2.0.dist-info/WHEEL
auto_subtitles_generator-0.2.0.dist-info/entry_points.txt
auto_subtitles_generator-0.2.0.dist-info/RECORD
